stringutils_happy/__init__.py
stringutils_happy/core.py
tests/__init__.py
tests/test_core.py
stringutils_happy-0.1.1.dist-info/METADATA
stringutils_happy-0.1.1.dist-info/WHEEL
stringutils_happy-0.1.1.dist-info/top_level.txt
stringutils_happy-0.1.1.dist-info/RECORD
