Metadata-Version: 2.1
Name: stringutils-happy
Version: 0.1.1
Summary: A utility library for string manipulation
Home-page: https://github.com/masakiShito/stringutils_happy
Author: Masaki Shito
Author-email: happy.engineer.life@gmail.com
License: UNKNOWN
Platform: UNKNOWN
Classifier: Programming Language :: Python :: 3
Classifier: License :: OSI Approved :: MIT License
Classifier: Operating System :: OS Independent
Requires-Python: >=3.6
